InteroperabilityEnabler/__init__.py
InteroperabilityEnabler/utils/__init__.py
InteroperabilityEnabler/utils/add_metadata.py
InteroperabilityEnabler/utils/data_formatter.py
InteroperabilityEnabler/utils/data_mapper.py
InteroperabilityEnabler/utils/extract_data.py
InteroperabilityEnabler/utils/merge_data.py
interoperabilityenabler-0.1.6.dist-info/METADATA
interoperabilityenabler-0.1.6.dist-info/WHEEL
interoperabilityenabler-0.1.6.dist-info/top_level.txt
interoperabilityenabler-0.1.6.dist-info/RECORD
